OpenFisca_Senegal-0.11.2.data/data/share/openfisca/openfisca-senegal/CHANGELOG.md
OpenFisca_Senegal-0.11.2.data/data/share/openfisca/openfisca-senegal/LICENSE
OpenFisca_Senegal-0.11.2.data/data/share/openfisca/openfisca-senegal/README.md
openfisca_senegal/__init__.py
openfisca_senegal/entities.py
openfisca_senegal/input_data_builder.py
openfisca_senegal/scenarios.py
openfisca_senegal/senegal_taxbenefitsystem.py
openfisca_senegal/survey_scenarios.py
openfisca_senegal/parameters/nombre_de_parts/limite_max.yaml
openfisca_senegal/parameters/nombre_de_parts/par_enfant.yaml
openfisca_senegal/parameters/nombre_de_parts/repartition_marie_conjoint.yaml
openfisca_senegal/parameters/nombre_de_parts/veuf_avec_enfant.yaml
openfisca_senegal/parameters/prelevements_obligatoires/impots_directs/bareme_impot_progressif.yaml
openfisca_senegal/parameters/prelevements_obligatoires/impots_directs/reductions_pour_charge_de_famille/max_1.yaml
openfisca_senegal/parameters/prelevements_obligatoires/impots_directs/reductions_pour_charge_de_famille/max_2.yaml
openfisca_senegal/parameters/prelevements_obligatoires/impots_directs/reductions_pour_charge_de_famille/max_3.yaml
openfisca_senegal/parameters/prelevements_obligatoires/impots_directs/reductions_pour_charge_de_famille/max_4.yaml
openfisca_senegal/parameters/prelevements_obligatoires/impots_directs/reductions_pour_charge_de_famille/max_5.yaml
openfisca_senegal/parameters/prelevements_obligatoires/impots_directs/reductions_pour_charge_de_famille/max_6.yaml
openfisca_senegal/parameters/prelevements_obligatoires/impots_directs/reductions_pour_charge_de_famille/max_7.yaml
openfisca_senegal/parameters/prelevements_obligatoires/impots_directs/reductions_pour_charge_de_famille/max_8.yaml
openfisca_senegal/parameters/prelevements_obligatoires/impots_directs/reductions_pour_charge_de_famille/max_9.yaml
openfisca_senegal/parameters/prelevements_obligatoires/impots_directs/reductions_pour_charge_de_famille/min_1.yaml
OpenFisca_Senegal-0.11.2.dist-info/LICENSE
OpenFisca_Senegal-0.11.2.dist-info/METADATA
OpenFisca_Senegal-0.11.2.dist-info/WHEEL
OpenFisca_Senegal-0.11.2.dist-info/top_level.txt
OpenFisca_Senegal-0.11.2.dist-info/RECORD
