Metadata-Version: 2.1
Name: OpenFisca-Senegal
Version: 0.11.2
Summary: Senegalese tax and benefit system for OpenFisca
Home-page: https://github.com/openfisca/senegal
Author: OpenFisca Team
Author-email: contact@openfisca.fr
License: http://www.fsf.org/licensing/licenses/agpl-3.0.html
Keywords: benefit microsimulation senegal social tax
Platform: UNKNOWN
License-File: LICENSE
Requires-Dist: OpenFisca-Core <42.0,>=41
Provides-Extra: ceq
Requires-Dist: openfisca-ceq >=0.4.1 ; extra == 'ceq'
Provides-Extra: dev
Requires-Dist: autopep8 ==1.5.5 ; extra == 'dev'
Requires-Dist: flake8 <7.0.0,>=6.0.0 ; extra == 'dev'
Requires-Dist: flake8-print ; extra == 'dev'
Requires-Dist: openfisca-survey-manager <=2.3,>=2 ; extra == 'dev'
Requires-Dist: pytest <8.0.0,>=7.2.2 ; extra == 'dev'
Requires-Dist: yamllint <1.27,>=1.11.1 ; extra == 'dev'
Requires-Dist: pandas ; extra == 'dev'
Provides-Extra: notebook
Requires-Dist: matplotlib ; extra == 'notebook'
Requires-Dist: notebook ; extra == 'notebook'
Requires-Dist: OpenFisca-Survey-Manager <=2.3,>=2 ; extra == 'notebook'
Requires-Dist: openpyxl ; extra == 'notebook'
Requires-Dist: pandas ; extra == 'notebook'
Requires-Dist: scipy ; extra == 'notebook'
Requires-Dist: xlrd ; extra == 'notebook'
Requires-Dist: xlwt ; extra == 'notebook'
Provides-Extra: survey
Requires-Dist: OpenFisca-Survey-Manager <=2.3,>=2 ; extra == 'survey'
Requires-Dist: scipy ; extra == 'survey'
